pyschemaconf/__init__.py
pyschemaconf/config.py
pyschemaconf-1.0.dist-info/METADATA
pyschemaconf-1.0.dist-info/RECORD
pyschemaconf-1.0.dist-info/WHEEL
pyschemaconf-1.0.dist-info/entry_points.txt
pyschemaconf-1.0.dist-info/top_level.txt
